{
  "hash": "5bdfb68e",
  "configHash": "c6906d4f",
  "lockfileHash": "ecca7c03",
  "browserHash": "87bb3aae",
  "optimized": {
    "vue": {
      "src": "../../../../node_modules/.pnpm/vue@3.5.32/node_modules/vue/dist/vue.runtime.esm-bundler.js",
      "file": "vue.js",
      "fileHash": "b0a5cc4e",
      "needsInterop": false
    },
    "vitepress > @vue/devtools-api": {
      "src": "../../../../node_modules/.pnpm/@vue+devtools-api@8.1.1/node_modules/@vue/devtools-api/dist/index.js",
      "file": "vitepress___@vue_devtools-api.js",
      "fileHash": "b5269142",
      "needsInterop": false
    },
    "vitepress > @vueuse/core": {
      "src": "../../../../node_modules/.pnpm/@vueuse+core@14.2.1_vue@3.5.32/node_modules/@vueuse/core/dist/index.js",
      "file": "vitepress___@vueuse_core.js",
      "fileHash": "5a279d39",
      "needsInterop": false
    },
    "vitepress-theme-teek": {
      "src": "../../../../node_modules/.pnpm/vitepress-theme-teek@1.5.6_vitepress@2.0.0-alpha.17_postcss@8.5.8__vue@3.5.32/node_modules/vitepress-theme-teek/es/index.mjs",
      "file": "vitepress-theme-teek.js",
      "fileHash": "14047a35",
      "needsInterop": false
    }
  },
  "chunks": {
    "chunk-P3XCKZ2X": {
      "file": "chunk-P3XCKZ2X.js"
    },
    "chunk-PZ5AY32C": {
      "file": "chunk-PZ5AY32C.js"
    }
  }
}